MANIFEST.in
README.md
requirements.txt
setup.py
kks/__init__.py
kks/cli.py
kks/config.py
kks/daemon.py
kks/exceptions.py
kks/generator.py
kks/libparser.py
kks/logger.py
kks/models.py
kks/parser.py
kks/renderer.py
kks/server.py
kks/utils.py
kks/res/config.toml
kks/res/src/sample.md
kks/res/theme/static/css/bootstrap.css
kks/res/theme/static/css/code.css
kks/res/theme/static/css/home.css
kks/res/theme/static/css/main.css
kks/res/theme/static/images/favicon.ico
kks/res/theme/static/images/logo.png
kks/res/theme/static/js/code.js
kks/res/theme/templates/layout.html
kks/res/theme/templates/page.html
kks/res/theme/templates/post.html
src/libparser.c