Metadata-Version: 1.1
Name: kks
Version: 1.1.0
Summary: a pithy and elegant python static blog
Home-page: https://github.com/kangkaisen/kks/
Author: kangkaisen
Author-email: kangkaisen@163.com
License: BSD
Keywords: static blog generator markdown,html
Platform: UNKNOWN
Classifier: Development Status :: 4 - Beta
Classifier: Environment :: Console
Classifier: Intended Audience :: Customer Service
Classifier: License :: OSI Approved :: BSD License
Classifier: Operating System :: POSIX
Classifier: Programming Language :: Python
